pytorch_concurrent_dataloader/__init__.py
pytorch_concurrent_dataloader/dataloader.py
pytorch_concurrent_dataloader/fetch.py
pytorch_concurrent_dataloader/worker.py
pytorch_concurrent_dataloader-0.0.7.dist-info/METADATA
pytorch_concurrent_dataloader-0.0.7.dist-info/WHEEL
pytorch_concurrent_dataloader-0.0.7.dist-info/top_level.txt
pytorch_concurrent_dataloader-0.0.7.dist-info/RECORD
